ngstream/__init__.py
ngstream/api.py
ngstream/utils.py
ngstream/protocols/__init__.py
ngstream/protocols/sra.py
ngstream/protocols/htsget/__init__.py
ngstream/protocols/htsget/_base.py
ngstream/protocols/htsget/_pysam.py
ngstream/protocols/htsget/_samtools.py
tests/__init__.py
tests/conftest.py
tests/mock_htsget.py
tests/real_htsget.py
tests/test_htsget.py
tests/test_sra.py
tests/test_utils.py
ngstream-0.2.2.dist-info/LICENSE
ngstream-0.2.2.dist-info/METADATA
ngstream-0.2.2.dist-info/WHEEL
ngstream-0.2.2.dist-info/entry_points.txt
ngstream-0.2.2.dist-info/top_level.txt
ngstream-0.2.2.dist-info/RECORD
