Metadata-Version: 2.1
Name: ngstream
Version: 0.2.2
Summary: Utilities for streaming NGS reads from SRA and GA4GH accessions.
Home-page: https://github.com/jdidion/ngstream
Author: John Didion
Author-email: github@didion.net
License: MIT
Platform: UNKNOWN
Classifier: Development Status :: 3 - Alpha
Classifier: Intended Audience :: Developers
Classifier: Topic :: Software Development :: Libraries :: Python Modules
Classifier: Topic :: Scientific/Engineering :: Bio-Informatics
Classifier: License :: OSI Approved :: MIT License
Classifier: Programming Language :: Python :: 3
Classifier: Programming Language :: Python :: 3.6
Requires-Dist: pokrok
Requires-Dist: xphyle (>=4.0.0)
Provides-Extra: pysam
Requires-Dist: pysam ; extra == 'pysam'
Provides-Extra: requests
Requires-Dist: requests ; extra == 'requests'
Provides-Extra: subby
Requires-Dist: subby (>=0.1.7) ; extra == 'subby'
